<?xml version="1.0"?>
<opencv_storage>
<stage6>
  <maxWeakCount>28</maxWeakCount>
  <stageThreshold>-6.4624142646789551e-01</stageThreshold>
  <weakClassifiers>
    <_>
      <internalNodes>
        0 -1 157760 5.1609184592962265e-03</internalNodes>
      <leafValues>
        2.2547331452369690e-01 -4.3812710046768188e-01</leafValues></_>
    <_>
      <internalNodes>
        0 -1 560 2.6786308735609055e-03</internalNodes>
      <leafValues>
        2.0816081762313843e-01 -3.5495433211326599e-01</leafValues></_>
    <_>
      <internalNodes>
        0 -1 162109 -2.2124471142888069e-03</internalNodes>
      <leafValues>
        -3.8279211521148682e-01 1.8717387318611145e-01</leafValues></_>
    <_>
      <internalNodes>
        0 -1 100334 -1.7147424817085266e-01</internalNodes>
      <leafValues>
        8.0238670110702515e-01 -8.1151932477951050e-02</leafValues></_>
    <_>
      <internalNodes>
        0 -1 159524 4.8455200158059597e-05</internalNodes>
      <leafValues>
        -2.5411871075630188e-01 2.4186693131923676e-01</leafValues></_>
    <_>
      <internalNodes>
        0 -1 147444 -3.8308021612465382e-03</internalNodes>
      <leafValues>
        5.6113648414611816e-01 -1.0414159297943115e-01</leafValues></_>
    <_>
      <internalNodes>
        0 -1 35053 5.0078528001904488e-03</internalNodes>
      <leafValues>
        -2.3042173683643341e-01 2.7899670600891113e-01</leafValues></_>
    <_>
      <internalNodes>
        0 -1 69827 -1.6202258848352358e-05</internalNodes>
      <leafValues>
        3.4492117166519165e-01 -2.1330296993255615e-01</leafValues></_>
    <_>
      <internalNodes>
        0 -1 153876 -5.0931647419929504e-02</internalNodes>
      <leafValues>
        5.3127896785736084e-01 -1.5389490127563477e-01</leafValues></_>
    <_>
      <internalNodes>
        0 -1 160863 -1.5286959242075682e-03</internalNodes>
      <leafValues>
        -3.7038403749465942e-01 2.3325450718402863e-01</leafValues></_>
    <_>
      <internalNodes>
        0 -1 85778 3.8244805182330310e-04</internalNodes>
      <leafValues>
        -1.4191280305385590e-01 4.6088027954101563e-01</leafValues></_>
    <_>
      <internalNodes>
        0 -1 26206 -2.9683413449674845e-03</internalNodes>
      <leafValues>
        -5.7161504030227661e-01 1.0662300884723663e-01</leafValues></_>
    <_>
      <internalNodes>
        0 -1 25986 4.0236503991764039e-05</internalNodes>
      <leafValues>
        -2.9188853502273560e-01 2.4452097713947296e-01</leafValues></_>
    <_>
      <internalNodes>
        0 -1 107790 7.5838454067707062e-03</internalNodes>
      <leafValues>
        -2.4600973725318909e-01 2.9563981294631958e-01</leafValues></_>
    <_>
      <internalNodes>
        0 -1 14716 1.3887090608477592e-03</internalNodes>
      <leafValues>
        2.1436062455177307e-01 -3.3539709448814392e-01</leafValues></_>
    <_>
      <internalNodes>
        0 -1 107294 -1.3868247158825397e-02</internalNodes>
      <leafValues>
        3.3171728253364563e-01 -2.5125119090080261e-01</leafValues></_>
    <_>
      <internalNodes>
        0 -1 44150 -1.0146333277225494e-01</internalNodes>
      <leafValues>
        -4.7810605168342590e-01 1.9820973277091980e-01</leafValues></_>
    <_>
      <internalNodes>
        0 -1 149761 1.2442137813195586e-04</internalNodes>
      <leafValues>
        -2.3324114084243774e-01 2.9385447502136230e-01</leafValues></_>
    <_>
      <internalNodes>
        0 -1 160984 -7.3454121593385935e-04</internalNodes>
      <leafValues>
        -4.0021196007728577e-01 1.7792686820030212e-01</leafValues></_>
    <_>
      <internalNodes>
        0 -1 85780 5.5173883447423577e-04</internalNodes>
      <leafValues>
        -1.1768809705972672e-01 6.4674180746078491e-01</leafValues></_>
    <_>
      <internalNodes>
        0 -1 161879 2.2971760481595993e-03</internalNodes>
      <leafValues>
        1.6083614528179169e-01 -4.9831324815750122e-01</leafValues></_>
    <_>
      <internalNodes>
        0 -1 15383 -5.5499477311968803e-03</internalNodes>
      <leafValues>
        -6.4180254936218262e-01 9.1293163597583771e-02</leafValues></_>
    <_>
      <internalNodes>
        0 -1 155688 2.6096682631759904e-05</internalNodes>
      <leafValues>
        -2.4722529947757721e-01 2.8863406181335449e-01</leafValues></_>
    <_>
      <internalNodes>
        0 -1 5000 -1.8893807427957654e-03</internalNodes>
      <leafValues>
        -4.1954892873764038e-01 1.6153058409690857e-01</leafValues></_>
    <_>
      <internalNodes>
        0 -1 161243 2.6100546165253036e-05</internalNodes>
      <leafValues>
        -2.7321332693099976e-01 2.5676307082176208e-01</leafValues></_>
    <_>
      <internalNodes>
        0 -1 64931 2.5652343174442649e-04</internalNodes>
      <leafValues>
        -2.1147006750106812e-01 3.5063907504081726e-01</leafValues></_>
    <_>
      <internalNodes>
        0 -1 133935 1.6160458326339722e-02</internalNodes>
      <leafValues>
        1.2081338465213776e-01 -6.4520281553268433e-01</leafValues></_>
    <_>
      <internalNodes>
        0 -1 126707 -6.9241560995578766e-03</internalNodes>
      <leafValues>
        4.2986586689949036e-01 -1.6804882884025574e-01</leafValues></_></weakClassifiers></stage6>
</opencv_storage>
